facerate/__init__.py
facerate/async_rate.py
facerate/base.py
facerate/exceptions.py
facerate/facerate.py
facerate/sync_rate.py
facerate/utils.py
facerate-0.0.1.dist-info/METADATA
facerate-0.0.1.dist-info/WHEEL
facerate-0.0.1.dist-info/entry_points.txt
facerate-0.0.1.dist-info/top_level.txt
facerate-0.0.1.dist-info/RECORD
